{
  "https://dena.com/": {
    "meta": {
      "url": "https://dena.com/",
      "domain": "dena_com",
      "slug": "top",
      "path": "/",
      "depth": 0,
      "capturedAt": "2026-06-19T07:53:07.699Z"
    },
    "assets": {
      "image": {
        "pc": "../screenshots/dena_com/top/dena_com_top_pc.webp",
        "sp": "../screenshots/dena_com/top/dena_com_top_sp.webp"
      },
      "video": {
        "pc": null,
        "sp": null
      },
      "thumb": {
        "pc": null,
        "sp": null
      }
    },
    "analysis": {
      "needsVideo": false,
      "animationHeavy": false,
      "hasWebGL": false,
      "hasScrollTrigger": false,
      "checked": {
        "auto": false,
        "manual": false
      }
    },
    "tags": []
  }
}